rabbitmq2solr/__init__.py
rabbitmq2solr-1.0.0.data/scripts/rabbitmq2solr
rabbitmq2solr-1.0.0.dist-info/LICENSE
rabbitmq2solr-1.0.0.dist-info/METADATA
rabbitmq2solr-1.0.0.dist-info/WHEEL
rabbitmq2solr-1.0.0.dist-info/top_level.txt
rabbitmq2solr-1.0.0.dist-info/RECORD
