Metadata-Version: 2.1
Name: rabbitmq2solr
Version: 1.0.0
Summary: RabbitMQ to Solr Indexer
Home-page: https://github.com/mantis-software-company/rabbitmq2solr
Author: Furkan Kalkan
Author-email: furkankalkan@mantis.com.tr
License: UNKNOWN
Platform: all
Classifier: License :: OSI Approved :: Apache Software License
Classifier: Topic :: Internet
Classifier: Topic :: Software Development
Classifier: Topic :: Utilities
Classifier: Intended Audience :: Developers
Classifier: Operating System :: MacOS
Classifier: Operating System :: POSIX
Classifier: Operating System :: Microsoft
Classifier: Programming Language :: Python
Classifier: Programming Language :: Python :: 3
Classifier: Programming Language :: Python :: 3.8
Requires-Python: >3.8.*, <4
Requires-Dist: aio-pika
Requires-Dist: httpx
Requires-Dist: orjson
